tests/ConstraintTest.py
tests/DataTest.py
tests/FunctionTest.py
tests/IndexTest.py
tests/ProcedureTest.py
tests/StructureTest.py
tests/TestDefinition.py
tests/TriggerTest.py
tests/ViewTest.py
tests/__init__.py
silmused-63.2.0.dist-info/LICENCE.txt
silmused-63.2.0.dist-info/METADATA
silmused-63.2.0.dist-info/WHEEL
silmused-63.2.0.dist-info/top_level.txt
silmused-63.2.0.dist-info/RECORD
