Metadata-Version: 2.1
Name: silmused
Version: 63.2.0
Home-page: https://github.com/kare22/silmused
Author: Karel Paan, Martti Kakk
Author-email: paan.karel@gmail.com
License: MIT License
License-File: LICENCE.txt
Requires-Dist: psycopg2
